{
  "state": "Indiana",
  "stateCode": "IN",
  "region": "na",
  "stanceDatacenter": "concerning",
  "stanceAI": "restrictive",
  "lastUpdated": "2026-04-13",
  "contextBlurb": "Indiana is reconsidering the sales-tax exemption it granted data centers and is weighing a bill that would require a state water-consumption permit before any data center can operate. Other pending legislation would force social-media companies to get parental consent for users under 14.",
  "legislation": [
    {
      "id": "in-sb0083",
      "billCode": "SB0083",
      "title": "Various utility matters.",
      "summary": "This Indiana bill makes several utility-related changes, including repealing a previously passed sales tax exemption for data centers and capping residential electricity rate increases at 3% per month. It also adjusts rules around municipal utility ownership and exempts utility service transactions from state sales tax starting in 2027.",
      "stage": "Committee",
      "stance": "concerning",
      "impactTags": [
        "energy-rates",
        "tax-incentives",
        "grid-capacity"
      ],
      "category": "data-center-energy",
      "updatedDate": "2025-12-08",
      "partyOrigin": "D",
      "sourceUrl": "https://iga.in.gov/legislative/2026/bills/senate/83/details",
      "legiscanUrl": "https://legiscan.com/IN/bill/SB0083/2026",
      "legiscanId": 2056672,
      "sponsors": [
        "Fady Qaddoura"
      ]
    },
    {
      "id": "in-hb1271",
      "billCode": "HB1271",
      "title": "Payment of health claims.",
      "summary": "This Indiana bill regulates how hospitals and insurers handle health insurance claims, including a ban on using automated systems to submit claims without human review by the provider. It also sets rules around payment assistance disclosures, overpayment recoupment timelines, and retroactive reimbursement rate reductions.",
      "stage": "Enacted",
      "stance": "restrictive",
      "impactTags": [
        "ai-in-healthcare"
      ],
      "category": "ai-healthcare",
      "updatedDate": "2026-03-04",
      "partyOrigin": "B",
      "sourceUrl": "https://iga.in.gov/legislative/2026/bills/house/1271/details",
      "legiscanUrl": "https://legiscan.com/IN/bill/HB1271/2026",
      "legiscanId": 2065548,
      "sponsors": [
        "Julie McGuire",
        "Lori Goss-Reaves",
        "Martin Carbaugh",
        "Victoria Garcia Wilburn"
      ]
    },
    {
      "id": "in-hb1178",
      "billCode": "HB1178",
      "title": "Minor access to social media.",
      "summary": "This Indiana bill requires social media companies to get parental consent before creating accounts for children under 14 and mandates age verification, parental controls, and strict data handling rules. Companies that violate these rules can be sued by the affected minor or their parent.",
      "stage": "Committee",
      "stance": "restrictive",
      "impactTags": [
        "child-safety",
        "data-privacy"
      ],
      "category": "data-privacy",
      "updatedDate": "2026-01-05",
      "partyOrigin": "R",
      "sourceUrl": "https://iga.in.gov/legislative/2026/bills/house/1178/details",
      "legiscanUrl": "https://legiscan.com/IN/bill/HB1178/2026",
      "legiscanId": 2065133,
      "sponsors": [
        "Joanna King",
        "Robert Behning",
        "Jake Teshka"
      ]
    },
    {
      "id": "in-hb1333",
      "billCode": "HB1333",
      "title": "Land use and development.",
      "summary": "This bill sets new rules for data centers in Indiana, requiring them to contribute at least 1% of their tax savings to local governments before receiving sales tax exemptions on equipment purchases. It also addresses land use on agricultural soils, battery energy storage systems, and requires emergency response documentation for large energy storage facilities.",
      "stage": "Committee",
      "stance": "concerning",
      "dimensionStances": {
        "environmental": "review",
        "energy": "favorable",
        "community": "concerning",
        "land-use": "concerning"
      },
      "impactTags": [
        "local-zoning",
        "tax-incentives",
        "local-control",
        "grid-capacity",
        "environmental-review"
      ],
      "category": "data-center-siting",
      "updatedDate": "2026-02-03",
      "partyOrigin": "R",
      "sourceUrl": "https://iga.in.gov/legislative/2026/bills/house/1333/details",
      "legiscanUrl": "https://legiscan.com/IN/bill/HB1333/2026",
      "legiscanId": 2065736,
      "sponsors": [
        "Kendell Culp",
        "Jim Pressel",
        "Craig Haggard",
        "Eric Koch"
      ]
    },
    {
      "id": "in-hb1043",
      "billCode": "HB1043",
      "title": "Data center water regulation.",
      "summary": "This bill requires data centers in Indiana to obtain a water consumption permit from the state's Department of Natural Resources before operating. It establishes an application and approval process to regulate how much water data centers can use.",
      "stage": "Committee",
      "stance": "concerning",
      "dimensionStances": {
        "environmental": "concerning",
        "energy": "none",
        "community": "review",
        "land-use": "none"
      },
      "impactTags": [
        "water-consumption",
        "water-infrastructure",
        "environmental-review",
        "local-zoning"
      ],
      "category": "data-center-energy",
      "updatedDate": "2025-12-02",
      "partyOrigin": "B",
      "sourceUrl": "https://iga.in.gov/legislative/2026/bills/house/1043/details",
      "legiscanUrl": "https://legiscan.com/IN/bill/HB1043/2026",
      "legiscanId": 2055884,
      "sponsors": [
        "Alex Burton",
        "Matt Commons"
      ]
    },
    {
      "id": "in-sb0079",
      "billCode": "SB0079",
      "title": "Data center development.",
      "summary": "This Indiana bill requires data centers to regularly report their electricity usage to state regulators and disclose projected power and water needs before receiving construction permits. It also creates a working group to study and forecast the future electricity demands of Indiana's data center industry.",
      "stage": "Committee",
      "stance": "concerning",
      "dimensionStances": {
        "energy": "review",
        "community": "review",
        "land-use": "concerning"
      },
      "impactTags": [
        "grid-capacity",
        "water-infrastructure",
        "energy-rates",
        "local-zoning",
        "local-control"
      ],
      "category": "data-center-energy",
      "updatedDate": "2025-12-08",
      "partyOrigin": "B",
      "sourceUrl": "https://iga.in.gov/legislative/2026/bills/senate/79/details",
      "legiscanUrl": "https://legiscan.com/IN/bill/SB0079/2026",
      "legiscanId": 2056628,
      "sponsors": [
        "J.D. Ford",
        "Spencer Deery"
      ]
    },
    {
      "id": "in-hb1201",
      "billCode": "HB1201",
      "title": "Various mental health and insurance matters.",
      "summary": "This Indiana bill bans the use of AI systems to impersonate or replace licensed mental health professionals, while also setting rules around insurance reimbursement and network adequacy for mental health services. The AI-specific provision is an outright prohibition, making it restrictive in that regard.",
      "stage": "Committee",
      "stance": "restrictive",
      "dimensionStances": {
        "ai-governance-dim": "restrictive",
        "ai-public": "restrictive"
      },
      "impactTags": [
        "ai-in-healthcare",
        "algorithmic-transparency"
      ],
      "category": "ai-healthcare",
      "updatedDate": "2026-01-05",
      "partyOrigin": "R",
      "sourceUrl": "https://iga.in.gov/legislative/2026/bills/house/1201/details",
      "legiscanUrl": "https://legiscan.com/IN/bill/HB1201/2026",
      "legiscanId": 2065139,
      "sponsors": [
        "Elizabeth Rowray",
        "Becky Cash",
        "Cindy Ledbetter",
        "Lori Goss-Reaves"
      ]
    }
  ]
}
